feat-0.29.9.dist-info/metadata.json
feat-0.29.9.dist-info/top_level.txt
feat-0.29.9.dist-info/METADATA
feat-0.29.9.dist-info/DESCRIPTION.rst
feat-0.29.9.dist-info/WHEEL
feat-0.29.9.dist-info/RECORD
feat-0.29.9.data/scripts/feat-dbload
feat-0.29.9.data/scripts/feat-couchpy
feat-0.29.9.data/scripts/feat-locate
feat-0.29.9.data/scripts/feat
feat-0.29.9.data/scripts/feat-service
feat/applications.py
feat/hacks.py
feat/__init__.py
feat/common/enum.py
feat/common/time.py
feat/common/log.py
feat/common/signal.py
feat/common/__init__.py
feat/common/timeout.py
feat/common/resolver.py
feat/common/registry.py
feat/common/_noarch_run.py
feat/common/manhole.py
feat/common/container.py
feat/common/journal.py
feat/common/annotate.py
feat/common/defer.py
feat/common/fiber.py
feat/common/guard.py
feat/common/mro.py
feat/common/fcntl.py
feat/common/error.py
feat/common/adapter.py
feat/common/benchmark.py
feat/common/connstr.py
feat/common/decorator.py
feat/common/text_helper.py
feat/common/run.py
feat/common/formatable.py
feat/common/reflect.py
feat/common/observer.py
feat/common/serialization/sexp.py
feat/common/serialization/__init__.py
feat/common/serialization/pytree.py
feat/common/serialization/json.py
feat/common/serialization/base.py
feat/common/serialization/banana.py
feat/common/serialization/adapters.py
feat/agents/application.py
feat/agents/__init__.py
feat/agents/dns/dns_agent.py
feat/agents/dns/__init__.py
feat/agents/dns/simulation.py
feat/agents/dns/api.py
feat/agents/dns/interface.py
feat/agents/dns/production.py
feat/agents/common/monitor.py
feat/agents/common/__init__.py
feat/agents/common/host.py
feat/agents/common/nagios.py
feat/agents/common/shard.py
feat/agents/common/start_agent.py
feat/agents/common/raage.py
feat/agents/common/dns.py
feat/agents/common/rpc.py
feat/agents/nagios/__init__.py
feat/agents/nagios/nagios_agent.py
feat/agents/host/host_agent.py
feat/agents/host/__init__.py
feat/agents/host/api.py
feat/agents/alert/__init__.py
feat/agents/alert/nagios.py
feat/agents/alert/simulation.py
feat/agents/alert/interface.py
feat/agents/alert/alert_agent.py
