Metadata-Version: 2.0
Name: feat
Version: 0.29.9
Summary: Flumotion Asynchronous Autonomous Agent Toolkit
Home-page: https://github.com/f3at/feat
Author: ('Flumotion Developers',)
Author-email: coreteam@flumotion.com
License: GPL
Download-URL: https://github.com/downloads/f3at/feat/feat-0.29.9.tar.gz
Keywords: twisted,agent,framework
Platform: any
Classifier: Development Status :: 4 - Beta
Classifier: Environment :: No Input/Output (Daemon)
Classifier: Intended Audience :: Developers
Classifier: License :: OSI Approved :: GNU General Public License (GPL)
Classifier: Natural Language :: English
Classifier: Operating System :: POSIX :: Linux
Classifier: Programming Language :: Python :: 2.6
Classifier: Topic :: Software Development :: Libraries :: Application Frameworks
Requires: json
Requires-Dist: zope.interface (>=3.6.0)
